ome_utils/__init__.py
hubmap_ome_utils-0.3.4.dist-info/LICENSE
hubmap_ome_utils-0.3.4.dist-info/METADATA
hubmap_ome_utils-0.3.4.dist-info/WHEEL
hubmap_ome_utils-0.3.4.dist-info/top_level.txt
hubmap_ome_utils-0.3.4.dist-info/RECORD
